yum2s3/__init__.py
yum2s3/auth.py
yum2s3/syncer/__init__.py
yum2s3-0.1.1.dist-info/DESCRIPTION.rst
yum2s3-0.1.1.dist-info/entry_points.txt
yum2s3-0.1.1.dist-info/METADATA
yum2s3-0.1.1.dist-info/metadata.json
yum2s3-0.1.1.dist-info/RECORD
yum2s3-0.1.1.dist-info/top_level.txt
yum2s3-0.1.1.dist-info/WHEEL
