Metadata-Version: 2.0
Name: yum2s3
Version: 0.1.1
Summary: Creates custom repositories in s3
Home-page: https://github.com/drewsonne/yum2s3
Author: Drew J. Sonne
Author-email: drew.sonne@gmail.com
License: UNKNOWN
Platform: UNKNOWN
Requires-Dist: Click
Requires-Dist: pyum
